qualitube/base.py
qualitube/channel.py
qualitube/exceptions.py
qualitube/log.py
qualitube/main.py
qualitube/playlist_items.py
qualitube/videos.py
qualitube-0.1.3.dist-info/entry_points.txt
qualitube-0.1.3.dist-info/LICENSE
qualitube-0.1.3.dist-info/WHEEL
qualitube-0.1.3.dist-info/METADATA
qualitube-0.1.3.dist-info/RECORD
