Metadata-Version: 2.1
Name: qualitube
Version: 0.1.3
Summary: A Python package for YouTube qualitative data analysis
License: MIT
Author: Vitor Mussa
Author-email: vtrmussa@gmail.com
Requires-Python: >=3.8,<4.0
Classifier: License :: OSI Approved :: MIT License
Classifier: Programming Language :: Python :: 3
Classifier: Programming Language :: Python :: 3.8
Classifier: Programming Language :: Python :: 3.9
Requires-Dist: pandas (>=1.2.4,<2.0.0)
Requires-Dist: requests (>=2.25.1,<3.0.0)
